cobramod/__init__.py
cobramod/debug.py
cobramod/error.py
cobramod/retrieval.py
cobramod/test.py
cobramod/utils.py
cobramod/core/__init__.py
cobramod/core/creation.py
cobramod/core/crossreferences.py
cobramod/core/extension.py
cobramod/core/genes.py
cobramod/core/graph.py
cobramod/core/pathway.py
cobramod/core/summary.py
cobramod/data/__init__.py
cobramod/data/textbook_biocyc.sbml
cobramod/data/textbook_biocyc_groups.sbml
cobramod/data/textbook_kegg.sbml
cobramod/parsing/__init__.py
cobramod/parsing/bigg.py
cobramod/parsing/biocyc.py
cobramod/parsing/db_version.py
cobramod/parsing/kegg.py
cobramod/parsing/plantcyc.py
cobramod/parsing/solcyc.py
cobramod/static/LICENSES.txt
cobramod/static/escher.mjs
cobramod/static/force_graph.mjs
cobramod/visualization/__init__.py
cobramod/visualization/converter.py
cobramod/visualization/debug.py
cobramod/visualization/escher.py
cobramod/visualization/force_graph.py
cobramod/visualization/items.py
cobramod/visualization/mapping.py
cobramod/visualization/pair.py
cobramod-1.3.0.dist-info/LICENSE
cobramod-1.3.0.dist-info/METADATA
cobramod-1.3.0.dist-info/WHEEL
cobramod-1.3.0.dist-info/top_level.txt
cobramod-1.3.0.dist-info/RECORD
