Metadata-Version: 2.1
Name: cobramod
Version: 1.3.0
Summary: Python package for pathway-centric modification and extension of genome-scale metabolic networks
Author-email: Stefano Camborda La Cruz <scambord@uni-koeln.de>, Jan-Niklas Weder <jweder@uni-koeln.de>, Nadine Töpfer <ntoepfer@uni-koeln.de>
Maintainer-email: Nadine Töpfer <ntoepfer@uni-koeln.de>
License: GNU GENERAL PUBLIC LICENSE
Project-URL: homepage, https://github.com/Toepfer-Lab/cobramod
Project-URL: Documentation, https://cobramod.readthedocs.io/
Project-URL: bugtracker, https://github.com/Toepfer-Lab/cobramod/issues
Keywords: genome-scale metabolic model,constraint-based modelling,COBRApy,Escher,metabolic model curation
Classifier: Intended Audience :: Science/Research
Classifier: License :: OSI Approved :: GNU General Public License v3 (GPLv3)
Classifier: Topic :: Scientific/Engineering :: Bio-Informatics
Requires-Python: >=3.10
License-File: LICENSE
Requires-Dist: colorlog
Requires-Dist: cobra >=0.29.0
Requires-Dist: requests >=2.31.0
Requires-Dist: tqdm >=4.62.3
Requires-Dist: openpyxl >=3.1.2
Requires-Dist: webcolors >=1.13
Requires-Dist: pyarrow >=14.0.2
Requires-Dist: anywidget >=0.9.9
Provides-Extra: dev
Requires-Dist: ruff ; extra == 'dev'
Requires-Dist: tox ; extra == 'dev'
Requires-Dist: sphinx ; extra == 'dev'
Requires-Dist: nbsphinx ; extra == 'dev'
Requires-Dist: sphinx-autoapi ; extra == 'dev'
Requires-Dist: jupyter-contrib-nbextensions ; extra == 'dev'
Requires-Dist: sphinx-rtd-theme ; extra == 'dev'
Requires-Dist: sphinxcontrib-napoleon ; extra == 'dev'
Requires-Dist: sphinxcontrib-bibtex ; extra == 'dev'
Provides-Extra: escher
Requires-Dist: escher-legacy >=1.7.4 ; extra == 'escher'
